morse_code/__init__.py
morse_code/morse.py
morse_tub-0.1.dist-info/LICENSE
morse_tub-0.1.dist-info/METADATA
morse_tub-0.1.dist-info/WHEEL
morse_tub-0.1.dist-info/top_level.txt
morse_tub-0.1.dist-info/RECORD
